kutils4p/__init__.py
kutils4p/logger.py
kutils4p/pkg_utils.py
kutils4p/data_structs/__init__.py
kutils4p/data_structs/accumulator.py
kutils4p/data_structs/linked_list.py
kutils4p/data_structs/ring_buffer.py
kutils4p/test/__init__.py
kutils4p-0.1.dist-info/METADATA
kutils4p-0.1.dist-info/RECORD
kutils4p-0.1.dist-info/WHEEL
kutils4p-0.1.dist-info/top_level.txt
