Metadata-Version: 2.1
Name: kutils4p
Version: 0.1
Summary: Simple everyday utils and data structs written in vanilla python3.
Home-page: https://github.com/ku-wolf/kutils4p
Author: Kevin Wolf
Author-email: kevinuwolf@gmail.com
License: gplv3.txt
Platform: UNKNOWN
Classifier: Programming Language :: Python :: 3
Classifier: Operating System :: OS Independent
Classifier: License :: OSI Approved :: GNU General Public License v3 (GPLv3)
Requires-Dist: appdirs
